Workbook

Sheet Executive_Dashboard
B2: EXECUTIVE SALES & PROFITABILITY DASHBOARD (FY2023)
B5: TOTAL REVENUE | E5: TOTAL NET PROFIT | H5: TOTAL UNITS SOLD
B6: =SUM(Cleaned_Data!H2:H101) | E6: =SUM(Cleaned_Data!J2:J101) | H6: =SUM(Cleaned_Data!F2:F101)
B10: Sales Rep | C10: Total Revenue | D10: Avg Profit Margin | F10: Region | G10: Revenue | H10: Units Sold
B11: Isabel Cross | C11: =SUMIFS(Cleaned_Data!H$2:H$101, Cleaned_Data!C$2:C$101, B11) | D11: =AVERAGEIFS(Cleaned_Data!I$2:I$101, Cleaned_Data!C$2:C$101, B11) | F11: North | G11: =SUMIFS(Cleaned_Data!H$2:H$101, Cleaned_Data!E$2:E$101, F11) | H11: =SUMIFS(Cleaned_Data!F$2:F$101, Cleaned_Data!E$2:E$101, F11)
B12: Cecilia Manning | C12: =SUMIFS(Cleaned_Data!H$2:H$101, Cleaned_Data!C$2:C$101, B12) | D12: =AVERAGEIFS(Cleaned_Data!I$2:I$101, Cleaned_Data!C$2:C$101, B12) | F12: South | G12: =SUMIFS(Cleaned_Data!H$2:H$101, Cleaned_Data!E$2:E$101, F12) | H12: =SUMIFS(Cleaned_Data!F$2:F$101, Cleaned_Data!E$2:E$101, F12)
B13: Shari Silva | C13: =SUMIFS(Cleaned_Data!H$2:H$101, Cleaned_Data!C$2:C$101, B13) | D13: =AVERAGEIFS(Cleaned_Data!I$2:I$101, Cleaned_Data!C$2:C$101, B13) | F13: East | G13: =SUMIFS(Cleaned_Data!H$2:H$101, Cleaned_Data!E$2:E$101, F13) | H13: =SUMIFS(Cleaned_Data!F$2:F$101, Cleaned_Data!E$2:E$101, F13)
B14: Albert Cook | C14: =SUMIFS(Cleaned_Data!H$2:H$101, Cleaned_Data!C$2:C$101, B14) | D14: =AVERAGEIFS(Cleaned_Data!I$2:I$101, Cleaned_Data!C$2:C$101, B14) | F14: West | G14: =SUMIFS(Cleaned_Data!H$2:H$101, Cleaned_Data!E$2:E$101, F14) | H14: =SUMIFS(Cleaned_Data!F$2:F$101, Cleaned_Data!E$2:E$101, F14)
B15: Brooks Vance | C15: =SUMIFS(Cleaned_Data!H$2:H$101, Cleaned_Data!C$2:C$101, B15) | D15: =AVERAGEIFS(Cleaned_Data!I$2:I$101, Cleaned_Data!C$2:C$101, B15)
B17: FILTER BY REGION: | C17: All
B19: Product Tier | C19: Filtered Units | D19: Filtered Revenue
B20: Enterprise Suite | C20: =IF(C$17="All", SUMIFS(Cleaned_Data!F$2:F$101, Cleaned_Data!D$2:D$101, B20), SUMIFS(Cleaned_Data!F$2:F$101, Cleaned_Data!D$2:D$101, B20, Cleaned_Data!E$2:E$101, C$17)) | D20: =IF(C$17="All", SUMIFS(Cleaned_Data!H$2:H$101, Cleaned_Data!D$2:D$101, B20), SUMIFS(Cleaned_Data!H$2:H$101, Cleaned_Data!D$2:D$101, B20, Cleaned_Data!E$2:E$101, C$17))
B21: Pro Cloud Plan | C21: =IF(C$17="All", SUMIFS(Cleaned_Data!F$2:F$101, Cleaned_Data!D$2:D$101, B21), SUMIFS(Cleaned_Data!F$2:F$101, Cleaned_Data!D$2:D$101, B21, Cleaned_Data!E$2:E$101, C$17)) | D21: =IF(C$17="All", SUMIFS(Cleaned_Data!H$2:H$101, Cleaned_Data!D$2:D$101, B21), SUMIFS(Cleaned_Data!H$2:H$101, Cleaned_Data!D$2:D$101, B21, Cleaned_Data!E$2:E$101, C$17))
B22: Hardware Node | C22: =IF(C$17="All", SUMIFS(Cleaned_Data!F$2:F$101, Cleaned_Data!D$2:D$101, B22), SUMIFS(Cleaned_Data!F$2:F$101, Cleaned_Data!D$2:D$101, B22, Cleaned_Data!E$2:E$101, C$17)) | D22: =IF(C$17="All", SUMIFS(Cleaned_Data!H$2:H$101, Cleaned_Data!D$2:D$101, B22), SUMIFS(Cleaned_Data!H$2:H$101, Cleaned_Data!D$2:D$101, B22, Cleaned_Data!E$2:E$101, C$17))
B23: Consulting Package | C23: =IF(C$17="All", SUMIFS(Cleaned_Data!F$2:F$101, Cleaned_Data!D$2:D$101, B23), SUMIFS(Cleaned_Data!F$2:F$101, Cleaned_Data!D$2:D$101, B23, Cleaned_Data!E$2:E$101, C$17)) | D23: =IF(C$17="All", SUMIFS(Cleaned_Data!H$2:H$101, Cleaned_Data!D$2:D$101, B23), SUMIFS(Cleaned_Data!H$2:H$101, Cleaned_Data!D$2:D$101, B23, Cleaned_Data!E$2:E$101, C$17))

Sheet Cleaned_Data
A1: Transaction_ID | B1: Date | C1: Sales_Rep | D1: Product | E1: Region | F1: Units_Sold | G1: Unit_Price | H1: Total_Revenue | I1: Profit_Margin_% | J1: Net_Profit
A2: TXN-1001 | B2: 45254 | C2: Isabel Cross | D2: Enterprise Suite | E2: East | F2: 20 | G2: 300 | H2: =F2*G2 | I2: 0.25 | J2: =H2*I2
A3: TXN-1002 | B3: 44979 | C3: Brooks Vance | D3: Enterprise Suite | E3: West | F3: 7 | G3: 150 | H3: =F3*G3 | I3: 0.2 | J3: =H3*I3
A4: TXN-1003 | B4: 45038 | C4: Cecilia Manning | D4: Enterprise Suite | E4: South | F4: 50 | G4: 1200 | H4: =F4*G4 | I4: 0.25 | J4: =H4*I4
A5: TXN-1004 | B5: 45156 | C5: Brooks Vance | D5: Hardware Node | E5: North | F5: 15 | G5: 1200 | H5: =F5*G5 | I5: 0.3 | J5: =H5*I5
A6: TXN-1005 | B6: 45069 | C6: Cecilia Manning | D6: Pro Cloud Plan | E6: East | F6: 11 | G6: 150 | H6: =F6*G6 | I6: 0.35 | J6: =H6*I6
A7: TXN-1006 | B7: 44976 | C7: Shari Silva | D7: Hardware Node | E7: East | F7: 7 | G7: 1200 | H7: =F7*G7 | I7: 0.2 | J7: =H7*I7
A8: TXN-1007 | B8: 45120 | C8: Isabel Cross | D8: Hardware Node | E8: East | F8: 41 | G8: 300 | H8: =F8*G8 | I8: 0.2 | J8: =H8*I8
A9: TXN-1008 | B9: 44950 | C9: Cecilia Manning | D9: Hardware Node | E9: North | F9: 19 | G9: 150 | H9: =F9*G9 | I9: 0.35 | J9: =H9*I9
A10: TXN-1009 | B10: 45069 | C10: Albert Cook | D10: Hardware Node | E10: South | F10: 28 | G10: 500 | H10: =F10*G10 | I10: 0.25 | J10: =H10*I10
A11: TXN-1010 | B11: 45270 | C11: Shari Silva | D11: Enterprise Suite | E11: South | F11: 39 | G11: 300 | H11: =F11*G11 | I11: 0.25 | J11: =H11*I11
A12: TXN-1011 | B12: 45163 | C12: Albert Cook | D12: Hardware Node | E12: South | F12: 48 | G12: 500 | H12: =F12*G12 | I12: 0.2 | J12: =H12*I12
A13: TXN-1012 | B13: 45044 | C13: Isabel Cross | D13: Hardware Node | E13: West | F13: 22 | G13: 150 | H13: =F13*G13 | I13: 0.25 | J13: =H13*I13
... A101: TXN-1100 | B101: 45037 | C101: Albert Cook | D101: Hardware Node | E101: East | F101: 11 | G101: 300 | H101: =F101*G101 | I101: 0.3 | J101: =H101*I101

Sheet Data_Dictionary
A1: Column Name | B1: Data Type | C1: Description | D1: Business Formula / Rule
A2: Transaction_ID | B2: String | C2: Unique identifier for each sales transaction | D2: Format: TXN-XXXX
A3: Date | B3: Date | C3: Date when transaction occurred in FY2023 | D3: YYYY-MM-DD
A4: Sales_Rep | B4: String | C4: Name of assigned sales representative | D4: Categorical (5 reps)
A5: Product | B5: String | C5: Product/Service tier purchased | D5: Categorical (4 tiers)
A6: Region | B6: String | C6: Geographic territory of client | D6: North, South, East, West
A7: Units_Sold | B7: Integer | C7: Quantity of units/licenses sold | D7: Range: 5 - 50
A8: Unit_Price | B8: Currency | C8: Unit cost in USD | D8: $150, $300, $500, $1200
A9: Total_Revenue | B9: Currency | C9: Gross sales value | D9: =Units_Sold * Unit_Price
A10: Profit_Margin_% | B10: Percentage | C10: Net profit margin percentage | D10: Range: 20.0% - 35.0%
A11: Net_Profit | B11: Currency | C11: Net profit generated after COGS | D11: =Total_Revenue * Profit_Margin_%
